{
    "kind": "youtube#searchListResponse",
    "etag": "JbMyMHlHGn2QMW10rBFpl-sbrQQ",
    "nextPageToken": "CAoQAA",
    "regionCode": "TN",
    "pageInfo": {
        "totalResults": 1000000,
        "resultsPerPage": 10
    },
    "items": [
        {
            "kind": "youtube#searchResult",
            "etag": "vXw1fZgs0IRxDWJrVT7WYwCofQY",
            "id": {
                "kind": "youtube#video",
                "videoId": "ywaIt2apNPE"
            },
            "snippet": {
                "publishedAt": "2023-04-01T12:28:39Z",
                "channelId": "UCySbEAyxxf2m2CFdSk0regQ",
                "title": "How to give directions in #english go straight/ corner/ go past. #englishlearning",
                "description": "how to give directions in #english go straight, turn left, at the corner #englishlearning #englishtips #learnenglish.",
                "thumbnails": {
                    "default": {
                        "url": "https://i.ytimg.com/vi/ywaIt2apNPE/default.jpg",
                        "width": 120,
                        "height": 90
                    },
                    "medium": {
                        "url": "https://i.ytimg.com/vi/ywaIt2apNPE/mqdefault.jpg",
                        "width": 320,
                        "height": 180
                    },
                    "high": {
                        "url": "https://i.ytimg.com/vi/ywaIt2apNPE/hqdefault.jpg",
                        "width": 480,
                        "height": 360
                    }
                },
                "channelTitle": "Miss English Teacher",
                "liveBroadcastContent": "none",
                "publishTime": "2023-04-01T12:28:39Z"
            }
        },
        {
            "kind": "youtube#searchResult",
            "etag": "Q7ZEJZIYdvHdlTz-IRHkntjORPs",
            "id": {
                "kind": "youtube#video",
                "videoId": "X61RR2Cd4QU"
            },
            "snippet": {
                "publishedAt": "2023-03-22T13:20:49Z",
                "channelId": "UCngfb3yWHPJ-yb0cOhU4k5A",
                "title": "Asia Now VS Past \ud83c\uddee\ud83c\uddf3\ud83c\uddef\ud83c\uddf5\ud83c\udde8\ud83c\uddf3\ud83c\uddf0\ud83c\uddf7.  #asia #india #japan #china #southkorea #countries #shorts #history",
                "description": "",
                "thumbnails": {
                    "default": {
                        "url": "https://i.ytimg.com/vi/X61RR2Cd4QU/default.jpg",
                        "width": 120,
                        "height": 90
                    },
                    "medium": {
                        "url": "https://i.ytimg.com/vi/X61RR2Cd4QU/mqdefault.jpg",
                        "width": 320,
                        "height": 180
                    },
                    "high": {
                        "url": "https://i.ytimg.com/vi/X61RR2Cd4QU/hqdefault.jpg",
                        "width": 480,
                        "height": 360
                    }
                },
                "channelTitle": "Yakoza Ball",
                "liveBroadcastContent": "none",
                "publishTime": "2023-03-22T13:20:49Z"
            }
        },
        {
            "kind": "youtube#searchResult",
            "etag": "AmT35Ai269ca5hZGX5FMi5vz55c",
            "id": {
                "kind": "youtube#video",
                "videoId": "polsnl_AUJ0"
            },
            "snippet": {
                "publishedAt": "2023-06-17T08:37:00Z",
                "channelId": "UCySbEAyxxf2m2CFdSk0regQ",
                "title": "How to speak fast like native speakers #learnenglish #englishtips",
                "description": "speak #english fast : #howtospeakenglishlikeanative don't say let me know say lemme know don't say do you want say wanna ...",
                "thumbnails": {
                    "default": {
                        "url": "https://i.ytimg.com/vi/polsnl_AUJ0/default.jpg",
                        "width": 120,
                        "height": 90
                    },
                    "medium": {
                        "url": "https://i.ytimg.com/vi/polsnl_AUJ0/mqdefault.jpg",
                        "width": 320,
                        "height": 180
                    },
                    "high": {
                        "url": "https://i.ytimg.com/vi/polsnl_AUJ0/hqdefault.jpg",
                        "width": 480,
                        "height": 360
                    }
                },
                "channelTitle": "Miss English Teacher",
                "liveBroadcastContent": "none",
                "publishTime": "2023-06-17T08:37:00Z"
            }
        },
        {
            "kind": "youtube#searchResult",
            "etag": "r93KXjDxkRpMU6m-7ZzezDGg8Dg",
            "id": {
                "kind": "youtube#video",
                "videoId": "fln9maTKoeY"
            },
            "snippet": {
                "publishedAt": "2023-02-05T10:19:38Z",
                "channelId": "UCngfb3yWHPJ-yb0cOhU4k5A",
                "title": "Relations with Pakistan \ud83c\uddf5\ud83c\uddf0 ( Europe &amp; Asia 2023) #pakistan #countries #relations #mapstudy #india",
                "description": "",
                "thumbnails": {
                    "default": {
                        "url": "https://i.ytimg.com/vi/fln9maTKoeY/default.jpg",
                        "width": 120,
                        "height": 90
                    },
                    "medium": {
                        "url": "https://i.ytimg.com/vi/fln9maTKoeY/mqdefault.jpg",
                        "width": 320,
                        "height": 180
                    },
                    "high": {
                        "url": "https://i.ytimg.com/vi/fln9maTKoeY/hqdefault.jpg",
                        "width": 480,
                        "height": 360
                    }
                },
                "channelTitle": "Yakoza Ball",
                "liveBroadcastContent": "none",
                "publishTime": "2023-02-05T10:19:38Z"
            }
        },
        {
            "kind": "youtube#searchResult",
            "etag": "UFdruM8lGYCELfpWYEjosJeCzfw",
            "id": {
                "kind": "youtube#video",
                "videoId": "OGI-KVwxsyM"
            },
            "snippet": {
                "publishedAt": "2023-04-22T10:40:58Z",
                "channelId": "UCySbEAyxxf2m2CFdSk0regQ",
                "title": "Leftovers, wrap up food to go #english #englishlearning #vocabulary",
                "description": "",
                "thumbnails": {
                    "default": {
                        "url": "https://i.ytimg.com/vi/OGI-KVwxsyM/default.jpg",
                        "width": 120,
                        "height": 90
                    },
                    "medium": {
                        "url": "https://i.ytimg.com/vi/OGI-KVwxsyM/mqdefault.jpg",
                        "width": 320,
                        "height": 180
                    },
                    "high": {
                        "url": "https://i.ytimg.com/vi/OGI-KVwxsyM/hqdefault.jpg",
                        "width": 480,
                        "height": 360
                    }
                },
                "channelTitle": "Miss English Teacher",
                "liveBroadcastContent": "none",
                "publishTime": "2023-04-22T10:40:58Z"
            }
        },
        {
            "kind": "youtube#searchResult",
            "etag": "kCv7Rsm6ySv7pZh9bhpmgRJY1pE",
            "id": {
                "kind": "youtube#video",
                "videoId": "l080zysfZL8"
            },
            "snippet": {
                "publishedAt": "2023-05-05T11:44:56Z",
                "channelId": "UCySbEAyxxf2m2CFdSk0regQ",
                "title": "Asthma, inhaler #english #learnenglish #englishtips",
                "description": "what do you call the thing for breathing : inhaler, asthma pronucnciaiton #english #learnenglish #vocabulary #englishtips.",
                "thumbnails": {
                    "default": {
                        "url": "https://i.ytimg.com/vi/l080zysfZL8/default.jpg",
                        "width": 120,
                        "height": 90
                    },
                    "medium": {
                        "url": "https://i.ytimg.com/vi/l080zysfZL8/mqdefault.jpg",
                        "width": 320,
                        "height": 180
                    },
                    "high": {
                        "url": "https://i.ytimg.com/vi/l080zysfZL8/hqdefault.jpg",
                        "width": 480,
                        "height": 360
                    }
                },
                "channelTitle": "Miss English Teacher",
                "liveBroadcastContent": "none",
                "publishTime": "2023-05-05T11:44:56Z"
            }
        },
        {
            "kind": "youtube#searchResult",
            "etag": "hyc0Hx_KgnHjXP5VBcFH_9ojCqw",
            "id": {
                "kind": "youtube#video",
                "videoId": "rDL8Q__hvPw"
            },
            "snippet": {
                "publishedAt": "2023-06-02T10:36:00Z",
                "channelId": "UCySbEAyxxf2m2CFdSk0regQ",
                "title": "Common mistakes in #english #englishtips #learnenglish",
                "description": "common mistakes to avoid in #english luggage is uncountable so X luggages but you can count suitcases, bags, and so on. when ...",
                "thumbnails": {
                    "default": {
                        "url": "https://i.ytimg.com/vi/rDL8Q__hvPw/default.jpg",
                        "width": 120,
                        "height": 90
                    },
                    "medium": {
                        "url": "https://i.ytimg.com/vi/rDL8Q__hvPw/mqdefault.jpg",
                        "width": 320,
                        "height": 180
                    },
                    "high": {
                        "url": "https://i.ytimg.com/vi/rDL8Q__hvPw/hqdefault.jpg",
                        "width": 480,
                        "height": 360
                    }
                },
                "channelTitle": "Miss English Teacher",
                "liveBroadcastContent": "none",
                "publishTime": "2023-06-02T10:36:00Z"
            }
        },
        {
            "kind": "youtube#searchResult",
            "etag": "Rg6YD1int0rb_U3YgSTyOz5LTLo",
            "id": {
                "kind": "youtube#video",
                "videoId": "w9BGi2ZPA_4"
            },
            "snippet": {
                "publishedAt": "2023-02-01T07:41:00Z",
                "channelId": "UCngfb3yWHPJ-yb0cOhU4k5A",
                "title": "Relations between Russia  and Europe &amp; Asia 2023. #russia #europe #asia #countries #mapstudy #shorts",
                "description": "",
                "thumbnails": {
                    "default": {
                        "url": "https://i.ytimg.com/vi/w9BGi2ZPA_4/default.jpg",
                        "width": 120,
                        "height": 90
                    },
                    "medium": {
                        "url": "https://i.ytimg.com/vi/w9BGi2ZPA_4/mqdefault.jpg",
                        "width": 320,
                        "height": 180
                    },
                    "high": {
                        "url": "https://i.ytimg.com/vi/w9BGi2ZPA_4/hqdefault.jpg",
                        "width": 480,
                        "height": 360
                    }
                },
                "channelTitle": "Yakoza Ball",
                "liveBroadcastContent": "none",
                "publishTime": "2023-02-01T07:41:00Z"
            }
        },
        {
            "kind": "youtube#searchResult",
            "etag": "KojRE8NtmlWgD0yFFHxoyPu7FCk",
            "id": {
                "kind": "youtube#video",
                "videoId": "u7r3hEpqx-4"
            },
            "snippet": {
                "publishedAt": "2022-05-28T16:55:44Z",
                "channelId": "UC1XJWy7kVElm4tzHnZtGszg",
                "title": "\u0643\u064a\u0641 \u062a\u0641\u0631\u0642 \u0628\u064a\u0646 \u0627\u0644\u0639\u0633\u0644 \u0627\u0644\u0645\u063a\u0634\u0648\u0634 \u0648 \u0627\u0644\u0639\u0633\u0644 \u0627\u0644\u0623\u0635\u0644\u064a \u0627\u0644\u062d\u0631 \u0648 \u0627\u0644\u0637\u0628\u064a\u0639\u064a ( \u0628\u0637\u0631\u064a\u0642\u0629 \u0628\u0633\u064a\u0637\u0629 )",
                "description": "\u0646\u0642\u062f\u0645 \u0644\u0643\u0645 \u0641\u064a \u0647\u0630\u0627 \u0627\u0644\u0641\u064a\u062f\u064a\u0648 \u0637\u0631\u064a\u0642\u0629 \u0628\u0633\u064a\u0637\u0629 \u0644\u0644\u062a\u0641\u0631\u064a\u0642 \u0628\u064a\u0646 \u0627\u0644\u0639\u0633\u0644 \u0627\u0644\u062d\u0631 \u0648 \u0627\u0644\u0639\u0633\u0644 \u0627\u0644\u0645\u063a\u0634\u0648\u0634 .. \u0643\u0644\u0646\u0627 \u064a\u0639\u0644\u0645 \u0623\u0646 \u0627\u0644\u0639\u0633\u0644 \u0645\u0627\u062f\u0629 \u062c\u062f\u0627 \u0645\u0641\u064a\u062f\u0629 \u0644\u0644\u062c\u0633\u0645 , \u0643\u0645\u0627 \u0623\u0646\u0647\u0627 ...",
                "thumbnails": {
                    "default": {
                        "url": "https://i.ytimg.com/vi/u7r3hEpqx-4/default.jpg",
                        "width": 120,
                        "height": 90
                    },
                    "medium": {
                        "url": "https://i.ytimg.com/vi/u7r3hEpqx-4/mqdefault.jpg",
                        "width": 320,
                        "height": 180
                    },
                    "high": {
                        "url": "https://i.ytimg.com/vi/u7r3hEpqx-4/hqdefault.jpg",
                        "width": 480,
                        "height": 360
                    }
                },
                "channelTitle": "Zoom show ",
                "liveBroadcastContent": "none",
                "publishTime": "2022-05-28T16:55:44Z"
            }
        },
        {
            "kind": "youtube#searchResult",
            "etag": "HjXZixbq0FQMbgPnMvJlPI0jr44",
            "id": {
                "kind": "youtube#video",
                "videoId": "rLF-6DZcqcU"
            },
            "snippet": {
                "publishedAt": "2015-09-03T13:59:18Z",
                "channelId": "UCCokNTo8zRK4mbpQQAjHBxQ",
                "title": "\u0637\u0631\u064a\u0642\u0629 \u062d\u0645\u0644 \u0627\u0644\u0628\u064a\u0628\u064a \u0627\u0644\u062a\u064a \u062a\u062e\u0641\u0641 \u0645\u0646 \u0627\u0644\u0623\u0644\u0645 \u0648 \u062a\u0633\u0645\u062d \u0628\u062e\u0631\u0648\u062c \u0627\u0644\u063a\u0627\u0632\u0627\u062a",
                "description": "\u0627\u0634\u062a\u0631\u0643 \u0641\u064a \u0642\u0646\u0627\u062a\u0646\u0627 \u0627\u0644\u062c\u062f\u064a\u062f\u0629: https://www.youtube.com/channel/UCvbfJ_oEPixRHMztKCrLMmA \u0644\u0645\u0639\u0631\u0641\u0629 \u0643\u0644 \u062c\u062f\u064a\u062f\u062f \u0645\u0648\u0642\u0639\u0646\u0627\u060c \u062a\u0627\u0628\u0639\u0648\u0646\u0627 \u0639\u0644\u0649: ...",
                "thumbnails": {
                    "default": {
                        "url": "https://i.ytimg.com/vi/rLF-6DZcqcU/default.jpg",
                        "width": 120,
                        "height": 90
                    },
                    "medium": {
                        "url": "https://i.ytimg.com/vi/rLF-6DZcqcU/mqdefault.jpg",
                        "width": 320,
                        "height": 180
                    },
                    "high": {
                        "url": "https://i.ytimg.com/vi/rLF-6DZcqcU/hqdefault.jpg",
                        "width": 480,
                        "height": 360
                    }
                },
                "channelTitle": "\u0645\u0646 \u0627\u0644\u0639\u0627\u0644\u0645",
                "liveBroadcastContent": "none",
                "publishTime": "2015-09-03T13:59:18Z"
            }
        }
    ]
}